django_year_calendar/__init__.py
django_year_calendar/admin.py
django_year_calendar/apps.py
django_year_calendar/models.py
django_year_calendar/tests.py
django_year_calendar/urls.py
django_year_calendar/utils.py
django_year_calendar/views.py
django_year_calendar/static/css/calendar1.css
django_year_calendar/templates/django_year_calendar/base.html
django_year_calendar/templates/django_year_calendar/base_bootstrap5.html
django_year_calendar/templates/django_year_calendar/base_event.html
django_year_calendar/templates/django_year_calendar/bootstrap5.html
django_year_calendar/templates/django_year_calendar/calendar_style.html
django_year_calendar/templates/django_year_calendar/custom.js
django_year_calendar/templates/django_year_calendar/events.js
django_year_calendar/templates/django_year_calendar/menu.html
django_year_calendar/templates/django_year_calendar/minimal.html
django_year_calendar/templates/django_year_calendar/select.js
django_year_calendar/templates/django_year_calendar/select_new.html
django_year_calendar/templates/django_year_calendar/selection.html
django_year_calendar/templates/django_year_calendar/selection_header.html
django_year_calendar/templates/django_year_calendar/standard_style.js
django_year_calendar-0.5.0.dist-info/LICENSE
django_year_calendar-0.5.0.dist-info/METADATA
django_year_calendar-0.5.0.dist-info/WHEEL
django_year_calendar-0.5.0.dist-info/top_level.txt
django_year_calendar-0.5.0.dist-info/RECORD
