Metadata-Version: 2.1
Name: django_year_calendar
Version: 0.5.0
Summary: A year calendar application for django
Home-page: https://github.com/esimorre/django-year-calendar
Project-URL: Bug Reports, https://github.com/esimorre/django-year-calendar/issues
Project-URL: Say Thanks!, https://year-calendar.github.io/
Project-URL: Source, https://github.com/esimorre/django-year-calendar
Keywords: django,calendar
Platform: any
Classifier: Development Status :: 4 - Beta
Classifier: Intended Audience :: Developers
Classifier: Topic :: Software Development :: Libraries :: Python Modules
Classifier: Framework :: Django
Classifier: License :: OSI Approved :: BSD License
Classifier: Programming Language :: Python :: 3
Classifier: Programming Language :: Python :: 3.7
Classifier: Programming Language :: Python :: 3.8
Classifier: Programming Language :: Python :: 3.9
Classifier: Programming Language :: Python :: 3.10
Classifier: Programming Language :: Python :: 3.11
Classifier: Programming Language :: Python :: 3.12
Classifier: Programming Language :: Python :: 3 :: Only
License-File: LICENSE
Requires-Dist: django
